{
    "1": {
        "userId": "331392389",
        "actionTime": "2021-02-18 23:48:22.412566",
        "reserveTime": "8:30",
        "guests": "4",
        "longTime": "Больше"
    },
    "2": {
        "userId": "331392389",
        "actionTime": "2021-02-22 22:41:11.451718",
        "reserveTime": "8:30",
        "guests": "4",
        "longTime": "Больше"
    },
    "3": {
        "userId": "331392389",
        "actionTime": "2021-02-22 23:01:02.082370",
        "reserveTime": "8:30",
        "guests": "4",
        "longTime": "Больше"
    },
    "4": {
        "userId": "331392389",
        "actionTime": "2021-02-22 23:48:58.484727",
        "reserveTime": "8:30",
        "guests": "4",
        "longTime": "Больше"
    },
    "5": {
        "userId": "331392389",
        "actionTime": "2021-02-22 23:49:48.200176",
        "reserveTime": "8:30",
        "guests": "4",
        "longTime": "Больше"
    },
    "6": {
        "userId": "331392389",
        "actionTime": "2021-02-22 23:50:31.527725",
        "reserveTime": "8:30",
        "guests": "4",
        "longTime": "Больше"
    },
    "7": {
        "userId": "331392389",
        "actionTime": "2021-02-22 23:51:12.209070",
        "reserveTime": "8:30",
        "guests": "4",
        "longTime": "Больше"
    },
    "8": {
        "userId": "331392389",
        "actionTime": "2021-02-22 23:52:40.596650",
        "reserveTime": "8:30",
        "guests": "4",
        "longTime": "Больше"
    },
    "9": {
        "userId": "331392389",
        "actionTime": "2021-02-23 18:05:23.405701",
        "reserveTime": "8:30",
        "guests": "4",
        "longTime": "Больше"
    },
    "10": {
        "userId": "331392389",
        "actionTime": "2021-03-06 09:00:34.564499"
    },
    "11": {
        "userId": "331392389",
        "actionTime": "2021-03-06 09:00:55.555327"
    },
    "12": {
        "userId": "331392389",
        "actionTime": "2021-03-06 09:01:24.256927"
    }
}